LICENSE
MANIFEST.in
readme.md
setup.py
docs/pypi.txt
valinor/__init__.py
valinor/elf.py
valinor/gdb.py
valinor/ide_detection.py
valinor/logging_setup.py
valinor/main.py
valinor.egg-info/PKG-INFO
valinor.egg-info/SOURCES.txt
valinor.egg-info/dependency_links.txt
valinor.egg-info/entry_points.txt
valinor.egg-info/requires.txt
valinor.egg-info/top_level.txt
valinor/test/__init__.py
valinor/test/cli.py
valinor/test/test_exporter.py
valinor/test/test_outputdir.py