Metadata-Version: 1.1
Name: valinor
Version: 1.1.0
Summary: Generate IDE project files to debug ELF files.
Home-page: about:blank
Author: Martin Kojtal, James Crosby
Author-email: c0170@rocketmail.com, James.Crosby@arm.com
License: Apache-2.0
Keywords: debug c cpp project generator embedded
Platform: UNKNOWN
Classifier: Development Status :: 3 - Alpha
Classifier: Topic :: Utilities
Classifier: License :: OSI Approved :: Apache Software License
Classifier: Environment :: Console
